viznu/__init__.py
viznu/core.py
viznu-0.2.5.dist-info/LICENSE
viznu-0.2.5.dist-info/METADATA
viznu-0.2.5.dist-info/WHEEL
viznu-0.2.5.dist-info/top_level.txt
viznu-0.2.5.dist-info/RECORD
