Metadata-Version: 2.1
Name: viznu
Version: 0.2.5
Home-page: https://github.com/apekshik/viznu
Author: Apekshik Panigrahi
Author-email: apekshik@gmail.com
Classifier: Programming Language :: Python :: 3
Classifier: License :: OSI Approved :: MIT License
Classifier: Operating System :: OS Independent
License-File: LICENSE
Requires-Dist: pandas
Requires-Dist: seaborn
Requires-Dist: matplotlib
